xstate_machine/__init__.py
xstate_machine/management/__init__.py
xstate_machine/management/commands/__init__.py
xstate_machine/management/commands/graph_transitions.py
xstate_machine/models.py
xstate_machine/signals.py
xstate_machine/tests/__init__.py
xstate_machine/tests/test_abstract_inheritance.py
xstate_machine/tests/test_basic_transitions.py
xstate_machine/tests/test_conditions.py
xstate_machine/tests/test_integer_field.py
xstate_machine/tests/test_key_field.py
xstate_machine/tests/test_protected_field.py
xstate_machine/tests/test_protected_fields.py
xstate_machine/tests/test_proxy_inheritance.py
xstate_machine-3.2.0.dist-info/LICENSE
xstate_machine-3.2.0.dist-info/METADATA
xstate_machine-3.2.0.dist-info/WHEEL
xstate_machine-3.2.0.dist-info/RECORD
